compos/__init__.py
compos/compos.py
compos/utils.py
compos-0.0.6.dist-info/METADATA
compos-0.0.6.dist-info/WHEEL
compos-0.0.6.dist-info/top_level.txt
compos-0.0.6.dist-info/RECORD
