Metadata-Version: 2.1
Name: compos
Version: 0.0.6
Summary: A Composer of Tables
Home-page: https://github.com/liao961120/compos
Author: Yongfu Liao
Author-email: liao961120@gmail.com
Classifier: Programming Language :: Python :: 3
Classifier: License :: OSI Approved :: MIT License
Classifier: Operating System :: OS Independent
Requires-Python: >=3.7
Requires-Dist: openpyxl
